{
  "model": "MLPRegressor",
  "hidden_layers": [
    256,
    128,
    64
  ],
  "n_folds": 10,
  "fold_results": [
    {
      "fold": 1,
      "rmse": 4.8352,
      "mae": 3.7551,
      "r2": 0.8806,
      "n_train": 2817,
      "n_test": 314,
      "n_iter": 55
    },
    {
      "fold": 2,
      "rmse": 5.4561,
      "mae": 4.1804,
      "r2": 0.842,
      "n_train": 2818,
      "n_test": 313,
      "n_iter": 73
    },
    {
      "fold": 3,
      "rmse": 5.5376,
      "mae": 4.2813,
      "r2": 0.8393,
      "n_train": 2818,
      "n_test": 313,
      "n_iter": 49
    },
    {
      "fold": 4,
      "rmse": 4.9761,
      "mae": 3.8952,
      "r2": 0.8571,
      "n_train": 2818,
      "n_test": 313,
      "n_iter": 40
    },
    {
      "fold": 5,
      "rmse": 5.5256,
      "mae": 4.0734,
      "r2": 0.851,
      "n_train": 2818,
      "n_test": 313,
      "n_iter": 52
    },
    {
      "fold": 6,
      "rmse": 4.5764,
      "mae": 3.4978,
      "r2": 0.9186,
      "n_train": 2818,
      "n_test": 313,
      "n_iter": 46
    },
    {
      "fold": 7,
      "rmse": 4.8605,
      "mae": 3.6584,
      "r2": 0.8927,
      "n_train": 2818,
      "n_test": 313,
      "n_iter": 66
    },
    {
      "fold": 8,
      "rmse": 4.7714,
      "mae": 3.6708,
      "r2": 0.8755,
      "n_train": 2818,
      "n_test": 313,
      "n_iter": 55
    },
    {
      "fold": 9,
      "rmse": 4.7525,
      "mae": 3.7613,
      "r2": 0.8755,
      "n_train": 2818,
      "n_test": 313,
      "n_iter": 43
    },
    {
      "fold": 10,
      "rmse": 5.7535,
      "mae": 4.3064,
      "r2": 0.7961,
      "n_train": 2818,
      "n_test": 313,
      "n_iter": 68
    }
  ],
  "overall": {
    "rmse": 5.1198,
    "mae": 3.908,
    "r2": 0.8668
  }
}